dcpmessage/__init__.py
dcpmessage/credentials.py
dcpmessage/dcp_message.py
dcpmessage/exceptions.py
dcpmessage/ldds_client.py
dcpmessage/ldds_message.py
dcpmessage/search_criteria.py
dcpmessage/utils.py
dcpmessage-1.3.1.dist-info/METADATA
dcpmessage-1.3.1.dist-info/WHEEL
dcpmessage-1.3.1.dist-info/top_level.txt
dcpmessage-1.3.1.dist-info/RECORD
