Metadata-Version: 2.4
Name: dcpmessage
Version: 1.3.1
Summary: package for retrieving GOES DCS message data from LRGS servers.
Author: dcpmessage authors
Requires-Python: >=3.13
